cpu_constant_library.v
//=========================================================================
// Name & Email must be EXACTLY as in Gradescope roster!
// Name: 
// Email: 
// 
// Assignment name: 
// Lab section: 
// TA: 
// 
// I hereby certify that I have not received assistance on this assignment,
// or used code, from ANY outside source other than the instruction team
// (apart from what was provided in the starter file).
//
//=========================================================================

//=========================================================================
//
// DO NOT CHANGE ANYTHING BELOW THIS COMMENT. IT IS PROVIDED TO MAKE SURE 
// YOUR LAB IS SUCCESSFULL. 
//
//=========================================================================

`timescale 1ns / 1ps

// --------------------------------------
// Opcodes 
// --------------------------------------

`define OPCODE_R_TYPE       6'b000000
`define OPCODE_LOAD_WORD    6'b100011
`define OPCODE_STORE_WORD   6'b101011
`define OPCODE_BRANCH_EQ    6'b000100
`define OPCODE_ADDI         6'b001000


// --------------------------------------
// Parameters
// --------------------------------------

`define ALU_AND  		 4'b0000
`define ALU_OR   		 4'b0001
`define ALU_ADD  		 4'b0010
`define ALU_SUBTRACT   4'b0110
`define ALU_LESS_THAN  4'b0111
`define ALU_NOR        4'b1100
  
`define FUNCT_AND   		6'b100100
`define FUNCT_OR    		6'b100101
`define FUNCT_ADD   		6'b100000
`define FUNCT_SUBTRACT 	6'b100010
`define FUNCT_LESS_THAN 6'b101010
`define FUNCT_NOR 		6'b100111

mux_2_1.v
//=========================================================================
// Name & Email must be EXACTLY as in Gradescope roster!
// Name: 
// Email: 
// 
// Assignment name: 
// Lab section: 
// TA: 
// 
// I hereby certify that I have not received assistance on this assignment,
// or used code, from ANY outside source other than the instruction team
// (apart from what was provided in the starter file).
//
//=========================================================================

//=========================================================================
//
// DO NOT CHANGE ANYTHING BELOW THIS COMMENT. IT IS PROVIDED TO MAKE SURE 
// YOUR LAB IS SUCCESSFULL. 
//
//=========================================================================

`timescale 1ns / 1ps

module mux_2_1 (select_in, datain1, datain2, data_out);

// Parameters 
parameter WORD_SIZE = 32 ; 

// Input and outputs 
// Modelling with Continuous Assignments 

input  wire select_in ;  
input  wire [WORD_SIZE-1:0] datain1 ; 
input  wire [WORD_SIZE-1:0] datain2 ; 
output wire [WORD_SIZE-1:0] data_out ;

assign data_out = (select_in) ? datain2 : datain1;

endmodule

alu.v
//=========================================================================
// Name & Email must be EXACTLY as in Gradescope roster!
// Name: 
// Email: 
// 
// Assignment name: 
// Lab section: 
// TA: 
// 
// I hereby certify that I have not received assistance on this assignment,
// or used code, from ANY outside source other than the instruction team
// (apart from what was provided in the starter file).
//
//=========================================================================

//=========================================================================
//
// DO NOT CHANGE ANYTHING BELOW THIS COMMENT. IT IS PROVIDED TO MAKE SURE 
// YOUR LAB IS SUCCESSFULL. 
//
//=========================================================================

`timescale 1ns / 1ps

`include "cpu_constant_library.v"

`define WORD_SIZE 32 

module alu (alu_control_in,  channel_a_in , channel_b_in , zero_out , alu_result_out);

// ---------------------------------------------------------
// Input output declarations 
// --------------------------------------------------------- 

input wire [3:0] alu_control_in ;  
input wire [`WORD_SIZE-1:0] channel_a_in ; 
input wire [`WORD_SIZE-1:0] channel_b_in ; 

output reg zero_out ; 
output reg [`WORD_SIZE-1:0] alu_result_out ; 

reg [`WORD_SIZE-1:0] temp ; 

// ---------------------------------------------------------
// Parameters 
// --------------------------------------------------------- 

always @(*) 

begin

	case (alu_control_in)   // R Type Instruction 
	
		`ALU_AND :      temp = channel_a_in & channel_b_in ; 
		`ALU_OR :       temp = channel_a_in | channel_b_in ; 
		`ALU_ADD :      temp = channel_a_in + channel_b_in ; 
		`ALU_SUBTRACT : temp = channel_a_in - channel_b_in ; 
		`ALU_NOR :  temp = ~ (channel_a_in | channel_b_in) ; 
		
		`ALU_LESS_THAN :  
		
						if (channel_a_in < channel_b_in) begin 
							temp = { `WORD_SIZE {1'b1} } ; 
						end 
						
						else begin 
							 temp = { `WORD_SIZE {1'b0} } ; 
						end  
		
		default : temp = { `WORD_SIZE {1'b0} } ; 
	
	endcase

	// Final results 
	
	alu_result_out = temp ; 
	zero_out = (temp == 0) ? 1 : 0 ; 

end 

endmodule

alu_control.v
//=========================================================================
// Name & Email must be EXACTLY as in Gradescope roster!
// Name: 
// Email: 
// 
// Assignment name: 
// Lab section: 
// TA: 
// 
// I hereby certify that I have not received assistance on this assignment,
// or used code, from ANY outside source other than the instruction team
// (apart from what was provided in the starter file).
//
//=========================================================================

//=========================================================================
//
// DO NOT CHANGE ANYTHING BELOW THIS COMMENT. IT IS PROVIDED TO MAKE SURE 
// YOUR LAB IS SUCCESSFULL. 
//
//=========================================================================

`timescale 1ns / 1ps

`include "cpu_constant_library.v"

module alu_control (	
	input wire [1:0]	alu_op,	
	input wire [5:0]	instruction_5_0,	
	output reg [3:0] 	alu_out   
);

always @(*)
begin 

 if (alu_op==2'b00) begin // LW and SW 
	alu_out = `ALU_ADD ; 
 end 

 else if (alu_op==2'b01) begin  // Branch 
		alu_out = `ALU_SUBTRACT ; 
 end 
	
 else begin 
	
	case (instruction_5_0)   // R Type Instruction 
		`FUNCT_AND : 		 alu_out = `ALU_AND ; 
		`FUNCT_OR  : 		 alu_out = `ALU_OR ; 
		`FUNCT_ADD : 		 alu_out = `ALU_ADD ; 
		`FUNCT_SUBTRACT  : alu_out = `ALU_SUBTRACT ; 
		`FUNCT_LESS_THAN : alu_out = `ALU_LESS_THAN ; 
		`FUNCT_NOR  : 		 alu_out = `ALU_NOR ; 
		default    :       alu_out = `ALU_ADD ;      
	endcase 
	
  end // End else 

end  // End block 

endmodule

cpu_registers.v
//=========================================================================
// Name & Email must be EXACTLY as in Gradescope roster!
// Name: 
// Email: 
// 
// Assignment name: 
// Lab section: 
// TA: 
// 
// I hereby certify that I have not received assistance on this assignment,
// or used code, from ANY outside source other than the instruction team
// (apart from what was provided in the starter file).
//
//=========================================================================

//=========================================================================
//
// DO NOT CHANGE ANYTHING BELOW THIS COMMENT. IT IS PROVIDED TO MAKE SURE 
// YOUR LAB IS SUCCESSFULL. 
//
//=========================================================================

`timescale 1ns / 1ps

`define MAX_REG 32
`define WORD_SIZE 32

module cpu_registers (
	 clk,	
    rst , 
    reg_write ,
    read_register_1 ,
    read_register_2 , 
    write_register , 
    write_data    ,  
    read_data_1  ,   
    read_data_2  
);

input wire clk, rst ,reg_write ; 
input wire [4:0] read_register_1; 
input wire [4:0] read_register_2 ; 

input wire [4:0]  write_register; 
input wire [`WORD_SIZE-1:0] write_data ; 

output wire [`WORD_SIZE-1:0] read_data_1 ; 
output wire [`WORD_SIZE-1:0] read_data_2 ; 

// -----------------------------------------------
// Memory Words and Locations  
// ----------------------------------------------- 	

reg [`WORD_SIZE-1:0] RFILE [`MAX_REG-1:0];
integer i;

// --------------------------------------
// Read statements 
// -------------------------------------- 

assign read_data_1 = RFILE[read_register_1] ; 
assign read_data_2 = RFILE[read_register_2] ; 
	
// ---------------------------------------------
// Write  
// --------------------------------------------- 

always @( posedge clk  )
begin 
	
       if ( rst )  begin 

	     for (i = 0; i < `MAX_REG; i = i +1) begin
			RFILE[i] <= { `WORD_SIZE {1'b0} } ; 
	     end 

       end else begin 

	     if (reg_write) begin 
			RFILE[write_register] <= write_data ;				
	     end 	

         end 
	
end 
	
endmodule

control_unit.v
//=========================================================================
// Name & Email must be EXACTLY as in Gradescope roster!
// Name: 
// Email: 
// 
// Assignment name: 
// Lab section: 
// TA: 
// 
// I hereby certify that I have not received assistance on this assignment,
// or used code, from ANY outside source other than the instruction team
// (apart from what was provided in the starter file).
//
//=========================================================================

//=========================================================================
//
// DO NOT CHANGE ANYTHING BELOW THIS COMMENT. IT IS PROVIDED TO MAKE SURE 
// YOUR LAB IS SUCCESSFULL. 
//
//=========================================================================

`timescale 1ns / 1ps

`include "cpu_constant_library.v"
 
module control_unit (
 input wire[5:0] instr_op   ,   
 output reg	 reg_dst    ,    
 output reg	 branch     ,  
 output reg  mem_read   ,   
 output reg	 mem_to_reg ,   
 output reg  [1:0]	 alu_op     ,  
 output reg  mem_write  ,    
 output reg	 alu_src    ,   
 output reg	 reg_write   );

always @(*)
begin 
	
    reg_dst     = 0;
    branch      = 0;
    mem_read    = 0;
    mem_to_reg  = 0;
    alu_op      = 0;
    mem_write   = 0;
    alu_src     = 0;
    reg_write   = 0;
	 
    case (instr_op)  

	   `OPCODE_R_TYPE :        
					
					begin 	
						reg_dst    = 1;
                  reg_write  = 1;
                  alu_op     = 2;
					end 
					
      `OPCODE_ADDI : 
						begin 
						 alu_src    = 1;
                   reg_write  = 1;
						end 
                                                
      `OPCODE_LOAD_WORD :  
						 begin 
							alu_src    = 1;
                     mem_to_reg = 1;
                     reg_write  = 1;
                     mem_read   = 1;
						 end  	
                                        
      `OPCODE_STORE_WORD :
						begin 
							alu_src    = 1;
							mem_write  = 1;
						end 
                                        
      `OPCODE_BRANCH_EQ :  
		
						begin 
							reg_dst  = 1;
							branch   = 1;
                     alu_op   = 1;
						end 	
                                        
      default :    branch = 0 ; 
        
    endcase;
	 
end 

endmodule

cpumemory.v
//=========================================================================
// Name & Email must be EXACTLY as in Gradescope roster!
// Name: 
// Email: 
// 
// Assignment name: 
// Lab section: 
// TA: 
// 
// I hereby certify that I have not received assistance on this assignment,
// or used code, from ANY outside source other than the instruction team
// (apart from what was provided in the starter file).
//
//=========================================================================

//=========================================================================
//
// DO NOT CHANGE ANYTHING BELOW THIS COMMENT. IT IS PROVIDED TO MAKE SURE 
// YOUR LAB IS SUCCESSFULL. 
//
//=========================================================================

`timescale 1ns / 1ps

`define NULL 0
`define MAX_REG 256

module cpumemory #(parameter WORD_SIZE=32,FILENAME="init.coe") (
    input wire clk,
    input wire rst,
    input wire[7:0] instr_read_address,
    output wire[WORD_SIZE-1:0] instr_instruction,
    input wire data_mem_write,   
    input [7:0] data_address,    
    input wire[WORD_SIZE-1:0] data_write_data ,    
    output wire[WORD_SIZE-1:0] data_read_data 

    //ignore memread signal, said in lecture 3/1

);

// ------------------------------------------
// Init memory 
// ------------------------------------------
	
reg [WORD_SIZE-1:0] buff [`MAX_REG-1:0];

initial begin 
	$readmemb(FILENAME, buff,0,255);
end 

// ------------------------------------------
// Read and Write block 
// ------------------------------------------ 

assign instr_instruction = buff[instr_read_address];
assign data_read_data = buff[data_address];
	
always @(posedge clk) begin 
	if (data_mem_write) begin 
		buff[data_address] = data_write_data;
	end
end 
endmodule

gen_register.v
//=========================================================================
// Name & Email must be EXACTLY as in Gradescope roster!
// Name: 
// Email: 
// 
// Assignment name: 
// Lab section: 
// TA: 
// 
// I hereby certify that I have not received assistance on this assignment,
// or used code, from ANY outside source other than the instruction team
// (apart from what was provided in the starter file).
//
//=========================================================================

//=========================================================================
//
// DO NOT CHANGE ANYTHING BELOW THIS COMMENT. IT IS PROVIDED TO MAKE SURE 
// YOUR LAB IS SUCCESSFULL. 
//
//=========================================================================

`timescale 1ns / 1ps

module gen_register (clk, rst, write_en, data_in, data_out);

parameter WORD_SIZE = 32 ; 

input wire clk , rst, write_en ;
input wire [WORD_SIZE-1:0] data_in ; 
output reg [WORD_SIZE-1:0] data_out; 

always @(posedge rst or posedge clk )
begin 

	if (rst)  begin 
		data_out <= { WORD_SIZE {1'b0} };
	end 
	else if (clk) begin
	
		if ( write_en )  begin 
			data_out  <= data_in ; 
		end 		
	end 

end 

endmodule

processor.v
//=========================================================================
// Name & Email must be EXACTLY as in Gradescope roster!
// Name: 
// Email: 
// 
// Assignment name: 
// Lab section: 
// TA: 
// 
// I hereby certify that I have not received assistance on this assignment,
// or used code, from ANY outside source other than the instruction team
// (apart from what was provided in the starter file).
//
//=========================================================================

`timescale 1ns / 1ps
`include "cpu_constant_library.v"
module processor #(parameter WORD_SIZE=32,MEM_FILE="init.coe") (
    input clk,
    input rst,   
	 // Debug signals 
    output [WORD_SIZE-1:0] prog_count, 
    output [5:0] instr_opcode,
    output [4:0] reg1_addr,
    output [WORD_SIZE-1:0] reg1_data,
    output [4:0] reg2_addr,
    output [WORD_SIZE-1:0] reg2_data,
    output [4:0] write_reg_addr,
    output [WORD_SIZE-1:0] write_reg_data 
);

// ----------------------------------------------
// Insert solution below here
// ----------------------------------------------

    assign prog_count = pc_out;
    assign instr_opcode = instruction_out[31:26];
    assign reg1_addr = instruction_out[25:21];
    assign reg2_addr = instruction_out[20:16];
    assign write_reg_addr = instruction_out[15:11];
    assign instr_extend = instruction_out[15:0]; //step 2?
    wire [WORD_SIZE-1:0] writeregmuxout;
    wire [WORD_SIZE-1:0] regdata1;
    wire [WORD_SIZE-1:0] regdata2;
    wire regdstselectin;
    wire branchandmux;
    wire memreaddatamem;
    wire memtoregmux;
    wire [1:0] aluopaluctrl;
    wire memwritedatamem;
    wire alusrcmux;
    wire regwriteregwrite;
    wire [WORD_SIZE-1:0] datamuxwritedataout;
    wire zero;
    wire [WORD_SIZE-1:0] aluout;
    wire [3:0] aluctrloutalu;
    wire [WORD_SIZE-1:0] alumuxout;
    wire [WORD_SIZE-1:0] datamemmuxchan2;
    wire [WORD_SIZE-1:0] pcadderout;
    wire [WORD_SIZE-1:0] step5muxchan2;

    alu pc_adder(
        .alu_control_in(`ALU_ADD), 
        .channel_a_in(pc_out), 
        .channel_b_in(32'h4), 
        .alu_result_out(pcadderout));

    //Wires for the PC
    wire [WORD_SIZE-1:0] pc_in;
    wire [WORD_SIZE-1:0] pc_out;

    gen_register PC(
        .clk(clk), 
        .rst(rst), 
        .write_en(clk), 
        .data_in(pc_in), 
        .data_out(pc_out));

    //Wires for the insruction
    wire [WORD_SIZE-1:0] instruction_out;

    cpumemory #(.FILENAME(MEM_FILE)) RAM( //Instruction memory, also for step 4 cpumemory module
        .clk(clk), 
        .rst(rst), 
        .instr_read_address(pc_out[7:0]), 
        .instr_instruction(instruction_out),
        .data_mem_write(memwritedatamem),
        .data_address(aluout[7:0]),
        .data_write_data(regdata2),
        .data_read_data(datamemmuxchan2)
    );   

    //STEP 2

    control_unit Control(
        .instr_op(instr_opcode),
        .reg_dst(regdstselectin), 
        .branch(branchandmux),
        .mem_read(memreaddatamem),
        .mem_to_reg(memtoregmux),
        .alu_op(aluopaluctrl),
        .mem_write(memwritedatamem),
        .alu_src(alusrcmux),
        .reg_write(regwriteregwrite));

    cpu_registers Registers(
        .clk(clk),
        .rst(rst),
        .reg_write(regwriteregwrite),
        .read_register_1(reg1_addr),
        .read_register_2(reg2_addr),
        .write_register(writeregmuxout[4:0]), //expects 5 bits 
        .write_data(datamuxwritedataout), 
        .read_data_1(regdata1), 
        .read_data_2(regdata2)); 

    mux_2_1 WriteRegMux(
        .select_in(regdstselectin),
        .datain1({27'd0, reg2_addr}),
        .datain2({27'd0, write_reg_addr}),
        .data_out(writeregmuxout));

    //STEP 3
    alu_control ALUControl(
        .alu_op(aluopaluctrl), 
        .instruction_5_0(instruction_out[5:0]),
        .alu_out(aluctrloutalu)); 

    

    mux_2_1 MuxAlu(
        .select_in(alusrcmux),
        .datain1(regdata2),
        .datain2({16'd0, instruction_out[15:0]}), //sign extend inst 15-0 to 32 bits
        .data_out(alumuxout));

    alu ALU(
        .alu_control_in(aluctrloutalu), 
        .channel_a_in(regdata1),
        .channel_b_in(alumuxout),
        .zero_out(zero),
        .alu_result_out(aluout));

    //STEP 4
    /*cpumemory DataMemory(
        .clk(clk),
        .rst(rst),
        //.instr_read_address(), TA says we can ignore these
        //.instr_instruction(),
        .data_mem_write(memwritedatamem),
        .data_address(aluout[7:0]),
        .data_write_data(regdata2),
        .data_read_data(datamemmuxchan2)); */

        //TA also said to ignore memread signal

    //STEP 5

    wire [WORD_SIZE-1:0] shiftleft2 = instruction_out[15:0] << 2;

    alu Step5(
        .alu_control_in(`ALU_ADD),
        .channel_a_in(pcadderout),
        .channel_b_in(shiftleft2),
        //.zero_out(), there is no zero in the image so 
        //i assume we can ignore
        .alu_result_out(step5muxchan2));

    wire step5muxand = branchandmux & zero; 

    mux_2_1 step5mux(
        .select_in(step5muxand),
        .datain1(pcadderout),
        .datain2(step5muxchan2),
        .data_out(pc_in)); 




endmodule

processor_tb.v
//=========================================================================
// Name & Email must be EXACTLY as in Gradescope roster!
// Name: Nicole Navarro  
// Email: nnava026@ucr.edu
// 
// Assignment name: Lab 5 - Single Cycle Datapath
// Lab section: 021
// TA: Jincong Lu
// 
// I hereby certify that I have not received assistance on this assignment,
// or used code, from ANY outside source other than the instruction team
// (apart from what was provided in the starter file).
//
//=========================================================================

`timescale 1ns / 1ps

module processor_tb;

// Inputs
reg clk;
reg rst;

// Outputs
wire [31:0] prog_count;
wire [5:0] instr_opcode;
wire [4:0] reg1_addr;
wire [31:0] reg1_data;
wire [4:0] reg2_addr;
wire [31:0] reg2_data;
wire [4:0] write_reg_addr;
wire [31:0] write_reg_data;

// -------------------------------------------------------
// Setup output file for possible debugging uses
// -------------------------------------------------------
initial begin
    $dumpfile("lab05.vcd");
    $dumpvars(0);
end

processor #(.MEM_FILE("individualInstructions.coe")) uut (
    .clk(clk),
    .rst(rst),
    .prog_count(prog_count),
    .instr_opcode(instr_opcode),
    .reg1_addr(reg1_addr),
    .reg1_data(reg1_data),
    .reg2_addr(reg2_addr),
    .reg2_data(reg2_data),
    .write_reg_addr(write_reg_addr),
    .write_reg_data(write_reg_data)
);
  
initial begin 
    clk = 0; rst = 1; #50; 
    clk = 1; rst = 1; #50; 
    clk = 0; rst = 0; 
         
    forever begin 
        #5 clk = ~clk;
    end 
end 

reg[31:0] result;
reg[31:0] expected;
integer last_instruction; 
integer passedTests = 0;
integer totalTests = 0;
initial begin
    /* Testing an entire program... last_instruction is the PC of the last instruction to execute */
    /*wait (prog_count == last_instruction)
    result = write_reg_data;
    $write("Test Case 1: (init.coe)...");
    totalTests = totalTests + 1;
    expected = 172;
    if (result == expected) begin
        passedTests = passedTests + 1;
        $display("passed.");
    end else begin
        $display("failed. Expected %0d but got %0d",expected,result);
    end*/

   /* Individual tests... Check the result after each instruction */
    @(negedge rst); // Wait for reset
    @(posedge clk); // Skip LW instruction

    @(posedge clk); #1; 
    totalTests = totalTests + 1;
    $write("Test Case %0d: add $a0, $v0, V1...", totalTests);
    if (write_reg_addr === 4 && write_reg_data === 535) begin
        passedTests = passedTests + 1;
        $display("passed.");
    end else begin
        $display("failed.");
    end

    @(posedge clk); #1;
    totalTests = totalTests + 1;
    $write("Test Case %0d: addi $a0, $v0, 100...", totalTests);
    if (write_reg_addr === 4 && write_reg_data === 461) begin
        passedTests = passedTests + 1;
        $display("passed.");
    end else begin
        $display("failed.");
    end

    $display("------------------------------------------------------------------");
    $display("Testing complete\nPassed %0d / %0d tests.",passedTests,totalTests);
    $display("------------------------------------------------------------------");
    $finish();
end
endmodule

lab05.vcd
$date
	Mon Mar 20 17:37:54 2023
$end
$version
	Icarus Verilog
$end
$timescale
	1ps
$end
$scope module processor_tb $end
$var wire 32 ! reg1_data [31:0] $end
$var wire 32 " reg2_data [31:0] $end
$var wire 32 # write_reg_data [31:0] $end
$var wire 5 $ write_reg_addr [4:0] $end
$var wire 5 % reg2_addr [4:0] $end
$var wire 5 & reg1_addr [4:0] $end
$var wire 32 ' prog_count [31:0] $end
$var wire 6 ( instr_opcode [5:0] $end
$var reg 1 ) clk $end
$var reg 1 * rst $end
$var integer 32 + passedTests [31:0] $end
$var integer 32 , totalTests [31:0] $end
$scope module uut $end
$var wire 1 ) clk $end
$var wire 32 - datamuxwritedataout [31:0] $end
$var wire 32 . prog_count [31:0] $end
$var wire 32 / reg1_data [31:0] $end
$var wire 32 0 reg2_data [31:0] $end
$var wire 1 * rst $end
$var wire 1 1 step5muxand $end
$var wire 32 2 write_reg_data [31:0] $end
$var wire 1 3 zero $end
$var wire 32 4 writeregmuxout [31:0] $end
$var wire 5 5 write_reg_addr [4:0] $end
$var wire 32 6 step5muxchan2 [31:0] $end
$var wire 32 7 shiftleft2 [31:0] $end
$var wire 1 8 regwriteregwrite $end
$var wire 1 9 regdstselectin $end
$var wire 32 : regdata2 [31:0] $end
$var wire 32 ; regdata1 [31:0] $end
$var wire 5 < reg2_addr [4:0] $end
$var wire 5 = reg1_addr [4:0] $end
$var wire 32 > pcadderout [31:0] $end
$var wire 32 ? pc_out [31:0] $end
$var wire 32 @ pc_in [31:0] $end
$var wire 1 A memwritedatamem $end
$var wire 1 B memtoregmux $end
$var wire 1 C memreaddatamem $end
$var wire 32 D instruction_out [31:0] $end
$var wire 6 E instr_opcode [5:0] $end
$var wire 1 F instr_extend $end
$var wire 32 G datamemmuxchan2 [31:0] $end
$var wire 1 H branchandmux $end
$var wire 1 I alusrcmux $end
$var wire 32 J aluout [31:0] $end
$var wire 2 K aluopaluctrl [1:0] $end
$var wire 32 L alumuxout [31:0] $end
$var wire 4 M aluctrloutalu [3:0] $end
$scope module ALU $end
$var wire 32 N channel_b_in [31:0] $end
$var wire 32 O channel_a_in [31:0] $end
$var wire 4 P alu_control_in [3:0] $end
$var reg 32 Q alu_result_out [31:0] $end
$var reg 32 R temp [31:0] $end
$var reg 1 3 zero_out $end
$upscope $end
$scope module ALUControl $end
$var wire 6 S instruction_5_0 [5:0] $end
$var wire 2 T alu_op [1:0] $end
$var reg 4 U alu_out [3:0] $end
$upscope $end
$scope module Control $end
$var wire 6 V instr_op [5:0] $end
$var reg 2 W alu_op [1:0] $end
$var reg 1 I alu_src $end
$var reg 1 H branch $end
$var reg 1 C mem_read $end
$var reg 1 B mem_to_reg $end
$var reg 1 A mem_write $end
$var reg 1 9 reg_dst $end
$var reg 1 8 reg_write $end
$upscope $end
$scope module MuxAlu $end
$var wire 32 X datain2 [31:0] $end
$var wire 1 I select_in $end
$var wire 32 Y datain1 [31:0] $end
$var wire 32 Z data_out [31:0] $end
$upscope $end
$scope module PC $end
$var wire 1 ) clk $end
$var wire 1 * rst $end
$var wire 1 ) write_en $end
$var wire 32 [ data_in [31:0] $end
$var reg 32 \ data_out [31:0] $end
$upscope $end
$scope module RAM $end
$var wire 1 ) clk $end
$var wire 8 ] data_address [7:0] $end
$var wire 1 A data_mem_write $end
$var wire 32 ^ data_read_data [31:0] $end
$var wire 32 _ instr_instruction [31:0] $end
$var wire 8 ` instr_read_address [7:0] $end
$var wire 1 * rst $end
$var wire 32 a data_write_data [31:0] $end
$upscope $end
$scope module Registers $end
$var wire 1 ) clk $end
$var wire 32 b read_data_1 [31:0] $end
$var wire 32 c read_data_2 [31:0] $end
$var wire 5 d read_register_1 [4:0] $end
$var wire 5 e read_register_2 [4:0] $end
$var wire 1 8 reg_write $end
$var wire 1 * rst $end
$var wire 32 f write_data [31:0] $end
$var wire 5 g write_register [4:0] $end
$var integer 32 h i [31:0] $end
$upscope $end
$scope module Step5 $end
$var wire 4 i alu_control_in [3:0] $end
$var wire 32 j channel_b_in [31:0] $end
$var wire 32 k channel_a_in [31:0] $end
$var reg 32 l alu_result_out [31:0] $end
$var reg 32 m temp [31:0] $end
$var reg 1 n zero_out $end
$upscope $end
$scope module WriteRegMux $end
$var wire 32 o datain1 [31:0] $end
$var wire 32 p datain2 [31:0] $end
$var wire 1 9 select_in $end
$var wire 32 q data_out [31:0] $end
$upscope $end
$scope module pc_adder $end
$var wire 4 r alu_control_in [3:0] $end
$var wire 32 s channel_a_in [31:0] $end
$var wire 32 t channel_b_in [31:0] $end
$var reg 32 u alu_result_out [31:0] $end
$var reg 32 v temp [31:0] $end
$var reg 1 w zero_out $end
$upscope $end
$scope module step5mux $end
$var wire 32 x datain1 [31:0] $end
$var wire 32 y datain2 [31:0] $end
$var wire 1 1 select_in $end
$var wire 32 z data_out [31:0] $end
$upscope $end
$upscope $end
$upscope $end
$enddefinitions $end
#0
$dumpvars
b100 z
b10000000 y
b100 x
0w
b100 v
b100 u
b100 t
b0 s
b10 r
b10 q
b0 p
b10 o
0n
b10000000 m
b10000000 l
b100 k
b1111100 j
b10 i
bx h
b10 g
bz f
b10 e
b0 d
bx c
bx b
bx a
b0 `
b10001100000000100000000000011111 _
bx ^
bx ]
b0 \
b100 [
b11111 Z
bx Y
b11111 X
b0 W
b100011 V
b10 U
b0 T
b11111 S
bx R
bx Q
b10 P
bx O
b11111 N
b10 M
b11111 L
b0 K
bx J
1I
0H
bx G
1F
b100011 E
b10001100000000100000000000011111 D
1C
1B
0A
b100 @
b0 ?
b100 >
b0 =
b10 <
bx ;
bx :
09
18
b1111100 7
b10000000 6
b0 5
b10 4
x3
bz 2
01
bz 0
bz /
b0 .
bz -
b0 ,
b0 +
1*
0)
b100011 (
b0 '
b0 &
b10 %
b0 $
bz #
bz "
bz !
$end
#50000
b1010110 G
b1010110 ^
b11111 ]
03
b11111 J
b11111 Q
b11111 R
b0 :
b0 Y
b0 a
b0 c
b0 ;
b0 O
b0 b
b100000 h
1)
#100000
0*
0)
#105000
b0 G
b0 ^
b1100 ]
b1100 J
b1100 Q
b1100 R
b101 g
b110000 7
b110000 j
b1100 L
b1100 N
b1100 Z
0F
b101 4
b101 q
18
1I
0B
0C
b1000 @
b1000 [
b1000 z
b111000 6
b111000 l
b111000 y
b111000 m
b1100 X
b1100 S
b101 o
b101 %
b101 <
b101 e
b11 &
b11 =
b11 d
b1000 (
b1000 E
b1000 V
b1000 >
b1000 k
b1000 u
b1000 x
b1000 v
b100000011001010000000000001100 D
b100000011001010000000000001100 _
b100 `
b100 '
b100 .
b100 ?
b100 \
b100 s
b0 :
b0 Y
b0 a
b0 c
1)
#110000
0)
#115000
b110 g
b10001100000000100000000000011111 G
b10001100000000100000000000011111 ^
b0 ]
b1100000010101000 7
b1100000010101000 j
b0 L
b0 N
b0 Z
b111 M
b111 P
b111 U
b110 4
b110 q
13
b0 J
b0 Q
b0 R
b10 K
b10 T
b10 W
19
18
0I
b1100 @
b1100 [
b1100 z
b1100000010110100 6
b1100000010110100 l
b1100000010110100 y
b1100000010110100 m
b11000000101010 X
b101010 S
b110 p
b110 $
b110 5
b100 o
b100 %
b100 <
b100 e
bz ;
bz O
bz b
b101 &
b101 =
b101 d
b0 (
b0 E
b0 V
b1100 >
b1100 k
b1100 u
b1100 x
b1100 v
b101001000011000000101010 D
b101001000011000000101010 _
b1000 `
b1000 '
b1000 .
b1000 ?
b1000 \
b1000 s
b0 :
b0 Y
b0 a
b0 c
1)
#116000
b1 ,
#120000
0)
#125000
b0 g
b0 7
b0 j
b10 M
b10 P
b10 U
b0 4
b0 q
b10000 @
b10000 [
b10000 z
b10000 6
b10000 l
b10000 y
b10000 m
b0 X
b0 S
b0 p
b0 $
b0 5
b0 o
b0 %
b0 <
b0 e
b0 ;
b0 O
b0 b
b0 &
b0 =
b0 d
b10000 >
b10000 k
b10000 u
b10000 x
b10000 v
b0 D
b0 _
b1100 `
b1100 '
b1100 .
b1100 ?
b1100 \
b1100 s
1)
#126000
b10 ,
