cpu_constant_library.v
//=========================================================================
// Name & Email must be EXACTLY as in Gradescope roster!
// Name: 
// Email: 
// 
// Assignment name: 
// Lab section: 
// TA: 
// 
// I hereby certify that I have not received assistance on this assignment,
// or used code, from ANY outside source other than the instruction team
// (apart from what was provided in the starter file).
//
//=========================================================================

//=========================================================================
//
// DO NOT CHANGE ANYTHING BELOW THIS COMMENT. IT IS PROVIDED TO MAKE SURE 
// YOUR LAB IS SUCCESSFULL. 
//
//=========================================================================

`timescale 1ns / 1ps

// --------------------------------------
// Opcodes 
// --------------------------------------

`define OPCODE_R_TYPE       6'b000000
`define OPCODE_LOAD_WORD    6'b100011
`define OPCODE_STORE_WORD   6'b101011
`define OPCODE_BRANCH_EQ    6'b000100
`define OPCODE_ADDI         6'b001000


// --------------------------------------
// Parameters
// --------------------------------------

`define ALU_AND  		 4'b0000
`define ALU_OR   		 4'b0001
`define ALU_ADD  		 4'b0010
`define ALU_SUBTRACT   4'b0110
`define ALU_LESS_THAN  4'b0111
`define ALU_NOR        4'b1100
  
`define FUNCT_AND   		6'b100100
`define FUNCT_OR    		6'b100101
`define FUNCT_ADD   		6'b100000
`define FUNCT_SUBTRACT 	6'b100010
`define FUNCT_LESS_THAN 6'b101010
`define FUNCT_NOR 		6'b100111

mux_2_1.v
//=========================================================================
// Name & Email must be EXACTLY as in Gradescope roster!
// Name: 
// Email: 
// 
// Assignment name: 
// Lab section: 
// TA: 
// 
// I hereby certify that I have not received assistance on this assignment,
// or used code, from ANY outside source other than the instruction team
// (apart from what was provided in the starter file).
//
//=========================================================================

//=========================================================================
//
// DO NOT CHANGE ANYTHING BELOW THIS COMMENT. IT IS PROVIDED TO MAKE SURE 
// YOUR LAB IS SUCCESSFULL. 
//
//=========================================================================

`timescale 1ns / 1ps

module mux_2_1 (select_in, datain1, datain2, data_out);

// Parameters 
parameter WORD_SIZE = 32 ; 

// Input and outputs 
// Modelling with Continuous Assignments 

input  wire select_in ;  
input  wire [WORD_SIZE-1:0] datain1 ; 
input  wire [WORD_SIZE-1:0] datain2 ; 
output wire [WORD_SIZE-1:0] data_out ;

assign data_out = (select_in) ? datain2 : datain1;

endmodule

alu.v
//=========================================================================
// Name & Email must be EXACTLY as in Gradescope roster!
// Name: 
// Email: 
// 
// Assignment name: 
// Lab section: 
// TA: 
// 
// I hereby certify that I have not received assistance on this assignment,
// or used code, from ANY outside source other than the instruction team
// (apart from what was provided in the starter file).
//
//=========================================================================

//=========================================================================
//
// DO NOT CHANGE ANYTHING BELOW THIS COMMENT. IT IS PROVIDED TO MAKE SURE 
// YOUR LAB IS SUCCESSFULL. 
//
//=========================================================================

`timescale 1ns / 1ps

`include "cpu_constant_library.v"

`define WORD_SIZE 32 

module alu (alu_control_in,  channel_a_in , channel_b_in , zero_out , alu_result_out);

// ---------------------------------------------------------
// Input output declarations 
// --------------------------------------------------------- 

input wire [3:0] alu_control_in ;  
input wire [`WORD_SIZE-1:0] channel_a_in ; 
input wire [`WORD_SIZE-1:0] channel_b_in ; 

output reg zero_out ; 
output reg [`WORD_SIZE-1:0] alu_result_out ; 

reg [`WORD_SIZE-1:0] temp ; 

// ---------------------------------------------------------
// Parameters 
// --------------------------------------------------------- 

always @(*) 

begin

	case (alu_control_in)   // R Type Instruction 
	
		`ALU_AND :      temp = channel_a_in & channel_b_in ; 
		`ALU_OR :       temp = channel_a_in | channel_b_in ; 
		`ALU_ADD :      temp = channel_a_in + channel_b_in ; 
		`ALU_SUBTRACT : temp = channel_a_in - channel_b_in ; 
		`ALU_NOR :  temp = ~ (channel_a_in | channel_b_in) ; 
		
		`ALU_LESS_THAN :  
		
						if (channel_a_in < channel_b_in) begin 
							temp = { `WORD_SIZE {1'b1} } ; 
						end 
						
						else begin 
							 temp = { `WORD_SIZE {1'b0} } ; 
						end  
		
		default : temp = { `WORD_SIZE {1'b0} } ; 
	
	endcase

	// Final results 
	
	alu_result_out = temp ; 
	zero_out = (temp == 0) ? 1 : 0 ; 

end 

endmodule

alu_control.v
//=========================================================================
// Name & Email must be EXACTLY as in Gradescope roster!
// Name: 
// Email: 
// 
// Assignment name: 
// Lab section: 
// TA: 
// 
// I hereby certify that I have not received assistance on this assignment,
// or used code, from ANY outside source other than the instruction team
// (apart from what was provided in the starter file).
//
//=========================================================================

//=========================================================================
//
// DO NOT CHANGE ANYTHING BELOW THIS COMMENT. IT IS PROVIDED TO MAKE SURE 
// YOUR LAB IS SUCCESSFULL. 
//
//=========================================================================

`timescale 1ns / 1ps

`include "cpu_constant_library.v"

module alu_control (	
	input wire [1:0]	alu_op,	
	input wire [5:0]	instruction_5_0,	
	output reg [3:0] 	alu_out   
);

always @(*)
begin 

 if (alu_op==2'b00) begin // LW and SW 
	alu_out = `ALU_ADD ; 
 end 

 else if (alu_op==2'b01) begin  // Branch 
		alu_out = `ALU_SUBTRACT ; 
 end 
	
 else begin 
	
	case (instruction_5_0)   // R Type Instruction 
		`FUNCT_AND : 		 alu_out = `ALU_AND ; 
		`FUNCT_OR  : 		 alu_out = `ALU_OR ; 
		`FUNCT_ADD : 		 alu_out = `ALU_ADD ; 
		`FUNCT_SUBTRACT  : alu_out = `ALU_SUBTRACT ; 
		`FUNCT_LESS_THAN : alu_out = `ALU_LESS_THAN ; 
		`FUNCT_NOR  : 		 alu_out = `ALU_NOR ; 
		default    :       alu_out = `ALU_ADD ;      
	endcase 
	
  end // End else 

end  // End block 

endmodule

cpu_registers.v
//=========================================================================
// Name & Email must be EXACTLY as in Gradescope roster!
// Name: 
// Email: 
// 
// Assignment name: 
// Lab section: 
// TA: 
// 
// I hereby certify that I have not received assistance on this assignment,
// or used code, from ANY outside source other than the instruction team
// (apart from what was provided in the starter file).
//
//=========================================================================

//=========================================================================
//
// DO NOT CHANGE ANYTHING BELOW THIS COMMENT. IT IS PROVIDED TO MAKE SURE 
// YOUR LAB IS SUCCESSFULL. 
//
//=========================================================================

`timescale 1ns / 1ps

`define MAX_REG 32
`define WORD_SIZE 32

module cpu_registers (
	 clk,	
    rst , 
    reg_write ,
    read_register_1 ,
    read_register_2 , 
    write_register , 
    write_data    ,  
    read_data_1  ,   
    read_data_2  
);

input wire clk, rst ,reg_write ; 
input wire [4:0] read_register_1; 
input wire [4:0] read_register_2 ; 

input wire [4:0]  write_register; 
input wire [`WORD_SIZE-1:0] write_data ; 

output wire [`WORD_SIZE-1:0] read_data_1 ; 
output wire [`WORD_SIZE-1:0] read_data_2 ; 

// -----------------------------------------------
// Memory Words and Locations  
// ----------------------------------------------- 	

reg [`WORD_SIZE-1:0] RFILE [`MAX_REG-1:0];
integer i;

// --------------------------------------
// Read statements 
// -------------------------------------- 

assign read_data_1 = RFILE[read_register_1] ; 
assign read_data_2 = RFILE[read_register_2] ; 
	
// ---------------------------------------------
// Write  
// --------------------------------------------- 

always @( posedge clk  )
begin 
	
       if ( rst )  begin 

	     for (i = 0; i < `MAX_REG; i = i +1) begin
			RFILE[i] <= { `WORD_SIZE {1'b0} } ; 
	     end 

       end else begin 

	     if (reg_write) begin 
			RFILE[write_register] <= write_data ;				
	     end 	

         end 
	
end 
	
endmodule

control_unit.v
//=========================================================================
// Name & Email must be EXACTLY as in Gradescope roster!
// Name: 
// Email: 
// 
// Assignment name: 
// Lab section: 
// TA: 
// 
// I hereby certify that I have not received assistance on this assignment,
// or used code, from ANY outside source other than the instruction team
// (apart from what was provided in the starter file).
//
//=========================================================================

//=========================================================================
//
// DO NOT CHANGE ANYTHING BELOW THIS COMMENT. IT IS PROVIDED TO MAKE SURE 
// YOUR LAB IS SUCCESSFULL. 
//
//=========================================================================

`timescale 1ns / 1ps

`include "cpu_constant_library.v"
 
module control_unit (
 input wire[5:0] instr_op   ,   
 output reg	 reg_dst    ,    
 output reg	 branch     ,  
 output reg  mem_read   ,   
 output reg	 mem_to_reg ,   
 output reg  [1:0]	 alu_op     ,  
 output reg  mem_write  ,    
 output reg	 alu_src    ,   
 output reg	 reg_write   );

always @(*)
begin 
	
    reg_dst     = 0;
    branch      = 0;
    mem_read    = 0;
    mem_to_reg  = 0;
    alu_op      = 0;
    mem_write   = 0;
    alu_src     = 0;
    reg_write   = 0;
	 
    case (instr_op)  

	   `OPCODE_R_TYPE :        
					
					begin 	
						reg_dst    = 1;
                  reg_write  = 1;
                  alu_op     = 2;
					end 
					
      `OPCODE_ADDI : 
						begin 
						 alu_src    = 1;
                   reg_write  = 1;
						end 
                                                
      `OPCODE_LOAD_WORD :  
						 begin 
							alu_src    = 1;
                     mem_to_reg = 1;
                     reg_write  = 1;
                     mem_read   = 1;
						 end  	
                                        
      `OPCODE_STORE_WORD :
						begin 
							alu_src    = 1;
							mem_write  = 1;
						end 
                                        
      `OPCODE_BRANCH_EQ :  
		
						begin 
							reg_dst  = 1;
							branch   = 1;
                     alu_op   = 1;
						end 	
                                        
      default :    branch = 0 ; 
        
    endcase;
	 
end 

endmodule

cpumemory.v
//=========================================================================
// Name & Email must be EXACTLY as in Gradescope roster!
// Name: 
// Email: 
// 
// Assignment name: 
// Lab section: 
// TA: 
// 
// I hereby certify that I have not received assistance on this assignment,
// or used code, from ANY outside source other than the instruction team
// (apart from what was provided in the starter file).
//
//=========================================================================

//=========================================================================
//
// DO NOT CHANGE ANYTHING BELOW THIS COMMENT. IT IS PROVIDED TO MAKE SURE 
// YOUR LAB IS SUCCESSFULL. 
//
//=========================================================================

`timescale 1ns / 1ps

`define NULL 0
`define MAX_REG 256

module cpumemory #(parameter WORD_SIZE=32,FILENAME="init.coe") (
    input wire clk,
    input wire rst,
    input wire[7:0] instr_read_address,
    output wire[WORD_SIZE-1:0] instr_instruction,
    input wire data_mem_write,   
    input [7:0] data_address,    
    input wire[WORD_SIZE-1:0] data_write_data ,    
    output wire[WORD_SIZE-1:0] data_read_data 

    //ignore memread signal, said in lecture 3/1

);

// ------------------------------------------
// Init memory 
// ------------------------------------------
	
reg [WORD_SIZE-1:0] buff [`MAX_REG-1:0];

initial begin 
	$readmemb(FILENAME, buff,0,255);
end 

// ------------------------------------------
// Read and Write block 
// ------------------------------------------ 

assign instr_instruction = buff[instr_read_address];
assign data_read_data = buff[data_address];
	
always @(posedge clk) begin 
	if (data_mem_write) begin 
		buff[data_address] = data_write_data;
	end
end 
endmodule

gen_register.v
//=========================================================================
// Name & Email must be EXACTLY as in Gradescope roster!
// Name: 
// Email: 
// 
// Assignment name: 
// Lab section: 
// TA: 
// 
// I hereby certify that I have not received assistance on this assignment,
// or used code, from ANY outside source other than the instruction team
// (apart from what was provided in the starter file).
//
//=========================================================================

//=========================================================================
//
// DO NOT CHANGE ANYTHING BELOW THIS COMMENT. IT IS PROVIDED TO MAKE SURE 
// YOUR LAB IS SUCCESSFULL. 
//
//=========================================================================

`timescale 1ns / 1ps

module gen_register (clk, rst, write_en, data_in, data_out);

parameter WORD_SIZE = 32 ; 

input wire clk , rst, write_en ;
input wire [WORD_SIZE-1:0] data_in ; 
output reg [WORD_SIZE-1:0] data_out; 

always @(posedge rst or posedge clk )
begin 

	if (rst)  begin 
		data_out <= { WORD_SIZE {1'b0} };
	end 
	else if (clk) begin
	
		if ( write_en )  begin 
			data_out  <= data_in ; 
		end 		
	end 

end 

endmodule

processor.v
//=========================================================================
// Name & Email must be EXACTLY as in Gradescope roster!
// Name: 
// Email: 
// 
// Assignment name: 
// Lab section: 
// TA: 
// 
// I hereby certify that I have not received assistance on this assignment,
// or used code, from ANY outside source other than the instruction team
// (apart from what was provided in the starter file).
//
//=========================================================================

`timescale 1ns / 1ps
`include "cpu_constant_library.v"
module processor #(parameter WORD_SIZE=32,MEM_FILE="init.coe") (
    input clk,
    input rst,   
	 // Debug signals 
    output [WORD_SIZE-1:0] prog_count, 
    output [5:0] instr_opcode,
    output [4:0] reg1_addr,
    output [WORD_SIZE-1:0] reg1_data,
    output [4:0] reg2_addr,
    output [WORD_SIZE-1:0] reg2_data,
    output [4:0] write_reg_addr,
    output [WORD_SIZE-1:0] write_reg_data 
);

// ----------------------------------------------
// Insert solution below here
// ----------------------------------------------

    assign prog_count = pc_out;
    assign instr_opcode = instruction_out[31:26];
    assign reg1_addr = instruction_out[25:21];
    assign reg2_addr = instruction_out[20:16];
    assign write_reg_addr = writeregmuxout;
    assign write_reg_data = step4muxout;
    assign instr_extend = instruction_out[15:0]; //step 2?
    wire [WORD_SIZE-1:0] step4muxout; 
    wire [WORD_SIZE-1:0] writeregmuxout;
    wire [WORD_SIZE-1:0] regdata1;
    wire [WORD_SIZE-1:0] regdata2;
    wire regdstselectin;
    wire branchandmux;
    wire memreaddatamem;
    wire memtoregmux;
    wire [1:0] aluopaluctrl;
    wire memwritedatamem;
    wire alusrcmux;
    wire regwriteregwrite;
    wire [WORD_SIZE-1:0] datamuxwritedataout;
    wire zero;
    wire [WORD_SIZE-1:0] aluout;
    wire [3:0] aluctrloutalu;
    wire [WORD_SIZE-1:0] alumuxout;
    wire [WORD_SIZE-1:0] datamemmuxchan2;
    wire [WORD_SIZE-1:0] pcadderout;
    wire [WORD_SIZE-1:0] step5muxchan2;

    alu pc_adder(
        .alu_control_in(`ALU_ADD), 
        .channel_a_in(pc_out), 
        .channel_b_in(32'h4), 
        .alu_result_out(pcadderout));

    //Wires for the PC
    wire [WORD_SIZE-1:0] pc_in;
    wire [WORD_SIZE-1:0] pc_out;

    gen_register PC(
        .clk(clk), 
        .rst(rst), 
        .write_en(clk), 
        .data_in(pc_in), 
        .data_out(pc_out));

    //Wires for the insruction
    wire [WORD_SIZE-1:0] instruction_out;

    cpumemory #(.FILENAME(MEM_FILE)) RAM( //Instruction memory, also for step 4 cpumemory module
        .clk(clk), 
        .rst(rst), 
        .instr_read_address(pc_out[9:2]), 
        .instr_instruction(instruction_out),
        .data_mem_write(memwritedatamem),
        .data_address(aluout[7:0]),
        .data_write_data(regdata2),
        .data_read_data(datamemmuxchan2)
    );   

    //STEP 2

    control_unit Control(
        .instr_op(instr_opcode),
        .reg_dst(regdstselectin), 
        .branch(branchandmux),
        .mem_read(memreaddatamem),
        .mem_to_reg(memtoregmux),
        .alu_op(aluopaluctrl),
        .mem_write(memwritedatamem),
        .alu_src(alusrcmux),
        .reg_write(regwriteregwrite));

    cpu_registers Registers(
        .clk(clk),
        .rst(rst),
        .reg_write(regwriteregwrite),
        .read_register_1(reg1_addr),
        .read_register_2(reg2_addr),
        .write_register(writeregmuxout[4:0]), //expects 5 bits 
        .write_data(datamuxwritedataout), 
        .read_data_1(regdata1), 
        .read_data_2(regdata2)); 

    mux_2_1 WriteRegMux(
        .select_in(regdstselectin),
        .datain1({27'd0, reg2_addr}),
        .datain2({27'd0, instruction_out[15:11]}),
        .data_out(writeregmuxout));

    //STEP 3
    alu_control ALUControl(
        .alu_op(aluopaluctrl), 
        .instruction_5_0(instruction_out[5:0]),
        .alu_out(aluctrloutalu)); 

    

    mux_2_1 MuxAlu(
        .select_in(alusrcmux),
        .datain1(regdata2),
        .datain2({16'd0, instruction_out[15:0]}), //sign extend inst 15-0 to 32 bits
        .data_out(alumuxout));

    alu ALU(
        .alu_control_in(aluctrloutalu), 
        .channel_a_in(regdata1),
        .channel_b_in(alumuxout),
        .zero_out(zero),
        .alu_result_out(aluout));

    //STEP 4
    mux_2_1 step4mux(
        .select_in(memtoregmux),
        .datain1(aluout),
        .datain2(datamemmuxchan2),
        .data_out(step4muxout));


    /*cpumemory DataMemory(
        .clk(clk),
        .rst(rst),
        //.instr_read_address(), TA says we can ignore these
        //.instr_instruction(),
        .data_mem_write(memwritedatamem),
        .data_address(aluout[7:0]),
        .data_write_data(regdata2),
        .data_read_data(datamemmuxchan2)); */

        //TA also said to ignore memread signal

    //STEP 5

    wire [WORD_SIZE-1:0] shiftleft2 = instruction_out[15:0] << 2;

    alu Step5(
        .alu_control_in(`ALU_ADD),
        .channel_a_in(pcadderout),
        .channel_b_in(shiftleft2),
        //.zero_out(), there is no zero in the image so 
        //i assume we can ignore
        .alu_result_out(step5muxchan2));

    wire step5muxand = branchandmux & zero; 

    mux_2_1 step5mux(
        .select_in(step5muxand),
        .datain1(pcadderout),
        .datain2(step5muxchan2),
        .data_out(pc_in)); 




endmodule

processor_tb.v
//=========================================================================
// Name & Email must be EXACTLY as in Gradescope roster!
// Name: Nicole Navarro  
// Email: nnava026@ucr.edu
// 
// Assignment name: Lab 5 - Single Cycle Datapath
// Lab section: 021
// TA: Jincong Lu
// 
// I hereby certify that I have not received assistance on this assignment,
// or used code, from ANY outside source other than the instruction team
// (apart from what was provided in the starter file).
//
//=========================================================================

`timescale 1ns / 1ps

module processor_tb;

// Inputs
reg clk;
reg rst;

// Outputs
wire [31:0] prog_count;
wire [5:0] instr_opcode;
wire [4:0] reg1_addr;
wire [31:0] reg1_data;
wire [4:0] reg2_addr;
wire [31:0] reg2_data;
wire [4:0] write_reg_addr;
wire [31:0] write_reg_data;

// -------------------------------------------------------
// Setup output file for possible debugging uses
// -------------------------------------------------------
initial begin
    $dumpfile("lab05.vcd");
    $dumpvars(0);
end

processor #(.MEM_FILE("individualInstructions.coe")) uut (
    .clk(clk),
    .rst(rst),
    .prog_count(prog_count),
    .instr_opcode(instr_opcode),
    .reg1_addr(reg1_addr),
    .reg1_data(reg1_data),
    .reg2_addr(reg2_addr),
    .reg2_data(reg2_data),
    .write_reg_addr(write_reg_addr),
    .write_reg_data(write_reg_data)
);
  
initial begin 
    clk = 0; rst = 1; #50; 
    clk = 1; rst = 1; #50; 
    clk = 0; rst = 0; 
         
    forever begin 
        #5 clk = ~clk;
    end 
end 

reg[31:0] result;
reg[31:0] expected;
integer last_instruction; 
integer passedTests = 0;
integer totalTests = 0;
initial begin
    /* Testing an entire program... last_instruction is the PC of the last instruction to execute */
    /*wait (prog_count == last_instruction)
    result = write_reg_data;
    $write("Test Case 1: (init.coe)...");
    totalTests = totalTests + 1;
    expected = 172;
    if (result == expected) begin
        passedTests = passedTests + 1;
        $display("passed.");
    end else begin
        $display("failed. Expected %0d but got %0d",expected,result);
    end*/

   /* Individual tests... Check the result after each instruction */
    @(negedge rst); // Wait for reset
    @(posedge clk); // Skip LW instruction

    @(posedge clk); #1; 
    totalTests = totalTests + 1;
    $write("Test Case %0d: add $a0, $v0, V1...", totalTests);
    if (write_reg_addr === 4 && write_reg_data === 535) begin
        passedTests = passedTests + 1;
        $display("passed.");
    end else begin
        $display("failed.");
    end

    @(posedge clk); #1;
    totalTests = totalTests + 1;
    $write("Test Case %0d: addi $a0, $v0, 100...", totalTests);
    if (write_reg_addr === 4 && write_reg_data === 461) begin
        passedTests = passedTests + 1;
        $display("passed.");
    end else begin
        $display("failed.");
    end

    $display("------------------------------------------------------------------");
    $display("Testing complete\nPassed %0d / %0d tests.",passedTests,totalTests);
    $display("------------------------------------------------------------------");
    $finish();
end
endmodule

lab05.vcd
$date
	Wed Mar 22 02:18:01 2023
$end
$version
	Icarus Verilog
$end
$timescale
	1ps
$end
$scope module processor_tb $end
$var wire 32 ! reg1_data [31:0] $end
$var wire 32 " reg2_data [31:0] $end
$var wire 32 # write_reg_data [31:0] $end
$var wire 5 $ write_reg_addr [4:0] $end
$var wire 5 % reg2_addr [4:0] $end
$var wire 5 & reg1_addr [4:0] $end
$var wire 32 ' prog_count [31:0] $end
$var wire 6 ( instr_opcode [5:0] $end
$var reg 1 ) clk $end
$var reg 1 * rst $end
$var integer 32 + passedTests [31:0] $end
$var integer 32 , totalTests [31:0] $end
$scope module uut $end
$var wire 1 ) clk $end
$var wire 32 - datamuxwritedataout [31:0] $end
$var wire 32 . prog_count [31:0] $end
$var wire 32 / reg1_data [31:0] $end
$var wire 32 0 reg2_data [31:0] $end
$var wire 1 * rst $end
$var wire 1 1 step5muxand $end
$var wire 32 2 write_reg_data [31:0] $end
$var wire 1 3 zero $end
$var wire 32 4 writeregmuxout [31:0] $end
$var wire 5 5 write_reg_addr [4:0] $end
$var wire 32 6 step5muxchan2 [31:0] $end
$var wire 32 7 step4muxout [31:0] $end
$var wire 32 8 shiftleft2 [31:0] $end
$var wire 1 9 regwriteregwrite $end
$var wire 1 : regdstselectin $end
$var wire 32 ; regdata2 [31:0] $end
$var wire 32 < regdata1 [31:0] $end
$var wire 5 = reg2_addr [4:0] $end
$var wire 5 > reg1_addr [4:0] $end
$var wire 32 ? pcadderout [31:0] $end
$var wire 32 @ pc_out [31:0] $end
$var wire 32 A pc_in [31:0] $end
$var wire 1 B memwritedatamem $end
$var wire 1 C memtoregmux $end
$var wire 1 D memreaddatamem $end
$var wire 32 E instruction_out [31:0] $end
$var wire 6 F instr_opcode [5:0] $end
$var wire 1 G instr_extend $end
$var wire 32 H datamemmuxchan2 [31:0] $end
$var wire 1 I branchandmux $end
$var wire 1 J alusrcmux $end
$var wire 32 K aluout [31:0] $end
$var wire 2 L aluopaluctrl [1:0] $end
$var wire 32 M alumuxout [31:0] $end
$var wire 4 N aluctrloutalu [3:0] $end
$scope module ALU $end
$var wire 32 O channel_b_in [31:0] $end
$var wire 32 P channel_a_in [31:0] $end
$var wire 4 Q alu_control_in [3:0] $end
$var reg 32 R alu_result_out [31:0] $end
$var reg 32 S temp [31:0] $end
$var reg 1 3 zero_out $end
$upscope $end
$scope module ALUControl $end
$var wire 6 T instruction_5_0 [5:0] $end
$var wire 2 U alu_op [1:0] $end
$var reg 4 V alu_out [3:0] $end
$upscope $end
$scope module Control $end
$var wire 6 W instr_op [5:0] $end
$var reg 2 X alu_op [1:0] $end
$var reg 1 J alu_src $end
$var reg 1 I branch $end
$var reg 1 D mem_read $end
$var reg 1 C mem_to_reg $end
$var reg 1 B mem_write $end
$var reg 1 : reg_dst $end
$var reg 1 9 reg_write $end
$upscope $end
$scope module MuxAlu $end
$var wire 32 Y datain2 [31:0] $end
$var wire 1 J select_in $end
$var wire 32 Z datain1 [31:0] $end
$var wire 32 [ data_out [31:0] $end
$upscope $end
$scope module PC $end
$var wire 1 ) clk $end
$var wire 1 * rst $end
$var wire 1 ) write_en $end
$var wire 32 \ data_in [31:0] $end
$var reg 32 ] data_out [31:0] $end
$upscope $end
$scope module RAM $end
$var wire 1 ) clk $end
$var wire 8 ^ data_address [7:0] $end
$var wire 1 B data_mem_write $end
$var wire 32 _ data_read_data [31:0] $end
$var wire 32 ` instr_instruction [31:0] $end
$var wire 8 a instr_read_address [7:0] $end
$var wire 1 * rst $end
$var wire 32 b data_write_data [31:0] $end
$upscope $end
$scope module Registers $end
$var wire 1 ) clk $end
$var wire 32 c read_data_1 [31:0] $end
$var wire 32 d read_data_2 [31:0] $end
$var wire 5 e read_register_1 [4:0] $end
$var wire 5 f read_register_2 [4:0] $end
$var wire 1 9 reg_write $end
$var wire 1 * rst $end
$var wire 32 g write_data [31:0] $end
$var wire 5 h write_register [4:0] $end
$var integer 32 i i [31:0] $end
$upscope $end
$scope module Step5 $end
$var wire 4 j alu_control_in [3:0] $end
$var wire 32 k channel_b_in [31:0] $end
$var wire 32 l channel_a_in [31:0] $end
$var reg 32 m alu_result_out [31:0] $end
$var reg 32 n temp [31:0] $end
$var reg 1 o zero_out $end
$upscope $end
$scope module WriteRegMux $end
$var wire 32 p datain1 [31:0] $end
$var wire 32 q datain2 [31:0] $end
$var wire 1 : select_in $end
$var wire 32 r data_out [31:0] $end
$upscope $end
$scope module pc_adder $end
$var wire 4 s alu_control_in [3:0] $end
$var wire 32 t channel_a_in [31:0] $end
$var wire 32 u channel_b_in [31:0] $end
$var reg 32 v alu_result_out [31:0] $end
$var reg 32 w temp [31:0] $end
$var reg 1 x zero_out $end
$upscope $end
$scope module step4mux $end
$var wire 32 y datain1 [31:0] $end
$var wire 32 z datain2 [31:0] $end
$var wire 1 C select_in $end
$var wire 32 { data_out [31:0] $end
$upscope $end
$scope module step5mux $end
$var wire 32 | datain1 [31:0] $end
$var wire 32 } datain2 [31:0] $end
$var wire 1 1 select_in $end
$var wire 32 ~ data_out [31:0] $end
$upscope $end
$upscope $end
$upscope $end
$enddefinitions $end
#0
$dumpvars
b100 ~
b10000000 }
b100 |
bx {
bx z
bx y
0x
b100 w
b100 v
b100 u
b0 t
b10 s
b10 r
b0 q
b10 p
0o
b10000000 n
b10000000 m
b100 l
b1111100 k
b10 j
bx i
b10 h
bz g
b10 f
b0 e
bx d
bx c
bx b
b0 a
b10001100000000100000000000011111 `
bx _
bx ^
b0 ]
b100 \
b11111 [
bx Z
b11111 Y
b0 X
b100011 W
b10 V
b0 U
b11111 T
bx S
bx R
b10 Q
bx P
b11111 O
b10 N
b11111 M
b0 L
bx K
1J
0I
bx H
1G
b100011 F
b10001100000000100000000000011111 E
1D
1C
0B
b100 A
b0 @
b100 ?
b0 >
b10 =
bx <
bx ;
0:
19
b1111100 8
bx 7
b10000000 6
b10 5
b10 4
x3
bx 2
01
bz 0
bz /
b0 .
bz -
b0 ,
b0 +
1*
0)
b100011 (
b0 '
b0 &
b10 %
b10 $
bx #
bz "
bz !
$end
#50000
b101101001 #
b101101001 2
b101101001 7
b101101001 {
b101101001 H
b101101001 _
b101101001 z
b11111 ^
03
b11111 K
b11111 R
b11111 y
b11111 S
b0 ;
b0 Z
b0 b
b0 d
b0 <
b0 P
b0 c
b100000 i
1)
#100000
0*
0)
#105000
b10101110 #
b10101110 2
b10101110 7
b10101110 {
b10101110 H
b10101110 _
b10101110 z
b100000 ^
b100000 K
b100000 R
b100000 y
b100000 S
b11 h
b11 $
b11 5
b10000000 8
b10000000 k
b100000 M
b100000 O
b100000 [
0G
b11 4
b11 r
b1000 A
b1000 \
b1000 ~
b10001000 6
b10001000 m
b10001000 }
b10001000 n
b100000 Y
b100000 T
b11 p
b11 %
b11 =
b11 f
b1000 ?
b1000 l
b1000 v
b1000 |
b1000 w
b10001100000000110000000000100000 E
b10001100000000110000000000100000 `
b1 a
b100 '
b100 .
b100 @
b100 ]
b100 t
b0 ;
b0 Z
b0 b
b0 d
1)
#110000
0)
#115000
b100 h
b100 $
b100 5
bx H
bx _
bx z
bx ^
b100 4
b100 r
bx #
bx 2
bx 7
bx {
b1000000010000000 8
b1000000010000000 k
bz M
bz O
bz [
x3
bx K
bx R
bx y
bx S
b10 L
b10 U
b10 X
1:
19
0J
0C
0D
b1100 A
b1100 \
b1100 ~
b1000000010001100 6
b1000000010001100 m
b1000000010001100 }
b1000000010001100 n
b10000000100000 Y
b100 q
bz <
bz P
bz c
b10 &
b10 >
b10 e
b0 (
b0 F
b0 W
b1100 ?
b1100 l
b1100 v
b1100 |
b1100 w
b10000110010000000100000 E
b10000110010000000100000 `
b10 a
b1000 '
b1000 .
b1000 @
b1000 ]
b1000 t
bz ;
bz Z
bz b
bz d
1)
#116000
b1 ,
#120000
0)
#125000
b1100100 M
b1100100 O
b1100100 [
b110010000 8
b110010000 k
1J
19
b0 L
b0 U
b0 X
0:
b10000 A
b10000 \
b10000 ~
b110100000 6
b110100000 m
b110100000 }
b110100000 n
b1100100 Y
b100100 T
b0 q
b100 p
b100 %
b100 =
b100 f
b1000 (
b1000 F
b1000 W
b10000 ?
b10000 l
b10000 v
b10000 |
b10000 w
b100000010001000000000001100100 E
b100000010001000000000001100100 `
b11 a
b1100 '
b1100 .
b1100 @
b1100 ]
b1100 t
1)
#126000
b10 ,
